lcd.v

`default_nettype none

module lcd (
    input            i_clk,
    input            i_reset,
    output     [7:0] o_lcd_data,
    output           o_lcd_rs,
    output           o_lcd_wr,
    input            i_lcd_fmark, // Unused for now

    // Pixel interface
    output [8:0] o_pixel_x,
    output [7:0] o_pixel_y,
    input [15:0] i_pixel_data
);

    reg reg_lcd_wr = 1'b1;
    reg reg_lcd_rs = 1'b1;
    reg [15:0] reg_lcd_data = 16'h0000;
    reg reg_pixel_byte = 1'b0;
    reg [8:0] reg_pixel_x = 0;
    reg [7:0] reg_pixel_y = 0;
    reg [8:0] reg_counter = 0;

    reg [7:0] state = 8'b0000_0001;

    // ILI9431 initialization sequence
    reg [6:0] init_sequence_counter = 0;
    reg [8:0] init_sequence[0:101];

    initial begin
        init_sequence[7'h00] = 9'h0ef;
        init_sequence[7'h01] = 9'h103;
        init_sequence[7'h02] = 9'h180;
        init_sequence[7'h03] = 9'h102;
        init_sequence[7'h04] = 9'h0cf; // Power control B
        init_sequence[7'h05] = 9'h100;
        init_sequence[7'h06] = 9'h1c1;
        init_sequence[7'h07] = 9'h130;
        init_sequence[7'h08] = 9'h0ed; // Power on sequence control
        init_sequence[7'h09] = 9'h164;
        init_sequence[7'h0a] = 9'h103;
        init_sequence[7'h0b] = 9'h112;
        init_sequence[7'h0c] = 9'h181;
        init_sequence[7'h0d] = 9'h0e8; // Driver timing control A
        init_sequence[7'h0e] = 9'h185;
        init_sequence[7'h0f] = 9'h100;
        init_sequence[7'h10] = 9'h178;
        init_sequence[7'h11] = 9'h0cb; // Power control A
        init_sequence[7'h12] = 9'h139;
        init_sequence[7'h13] = 9'h12c;
        init_sequence[7'h14] = 9'h100;
        init_sequence[7'h15] = 9'h134;
        init_sequence[7'h16] = 9'h102;
        init_sequence[7'h17] = 9'h0f7; // Pump ratio control
        init_sequence[7'h18] = 9'h120;
        init_sequence[7'h19] = 9'h0ea; // Driver timing control B
        init_sequence[7'h1a] = 9'h100;
        init_sequence[7'h1b] = 9'h100;
        init_sequence[7'h1c] = 9'h0c0; // Power control 1
        init_sequence[7'h1d] = 9'h123;
        init_sequence[7'h1e] = 9'h0c1; // Power control 2
        init_sequence[7'h1f] = 9'h110;
        init_sequence[7'h20] = 9'h0c5; // VCOM Control 1
        init_sequence[7'h21] = 9'h13e;
        init_sequence[7'h22] = 9'h128;
        init_sequence[7'h23] = 9'h0c7; // VCOM Control 2
        init_sequence[7'h24] = 9'h186;
        init_sequence[7'h25] = 9'h036; // Memory Access Control
        init_sequence[7'h26] = 9'h148;
        init_sequence[7'h27] = 9'h03a;
        init_sequence[7'h28] = 9'h155;
        init_sequence[7'h29] = 9'h0b1;
        init_sequence[7'h2a] = 9'h100;
        init_sequence[7'h2b] = 9'h118;
        init_sequence[7'h2c] = 9'h0b6;
        init_sequence[7'h2d] = 9'h108;
        init_sequence[7'h2e] = 9'h182;
        init_sequence[7'h2f] = 9'h127;
        init_sequence[7'h30] = 9'h0f2;
        init_sequence[7'h31] = 9'h100;
        init_sequence[7'h32] = 9'h026;
        init_sequence[7'h33] = 9'h101;
        init_sequence[7'h34] = 9'h0e0;
        init_sequence[7'h35] = 9'h10f;
        init_sequence[7'h36] = 9'h131;
        init_sequence[7'h37] = 9'h12b;
        init_sequence[7'h38] = 9'h10c;
        init_sequence[7'h39] = 9'h10e;
        init_sequence[7'h3a] = 9'h108;
        init_sequence[7'h3b] = 9'h14e;
        init_sequence[7'h3c] = 9'h1f1;
        init_sequence[7'h3d] = 9'h137;
        init_sequence[7'h3e] = 9'h107;
        init_sequence[7'h3f] = 9'h110;
        init_sequence[7'h40] = 9'h103;
        init_sequence[7'h41] = 9'h10e;
        init_sequence[7'h42] = 9'h109;
        init_sequence[7'h43] = 9'h100;
        init_sequence[7'h44] = 9'h0e1;
        init_sequence[7'h45] = 9'h100;
        init_sequence[7'h46] = 9'h10e;
        init_sequence[7'h47] = 9'h114;
        init_sequence[7'h48] = 9'h103;
        init_sequence[7'h49] = 9'h111;
        init_sequence[7'h4a] = 9'h107;
        init_sequence[7'h4b] = 9'h131;
        init_sequence[7'h4c] = 9'h1c1;
        init_sequence[7'h4d] = 9'h148;
        init_sequence[7'h4e] = 9'h108;
        init_sequence[7'h4f] = 9'h10f;
        init_sequence[7'h50] = 9'h10c;
        init_sequence[7'h51] = 9'h131;
        init_sequence[7'h52] = 9'h136;
        init_sequence[7'h53] = 9'h10f;
        init_sequence[7'h54] = 9'h011; // Sleep Out
        init_sequence[7'h55] = 9'h029; // Display ON
        init_sequence[7'h56] = 9'h036; // Memory Access Control
        init_sequence[7'h57] = 9'h108; //   Select BGR color filter, per LCD different color sequence
        init_sequence[7'h58] = 9'h02a; // Column Address Set
        init_sequence[7'h59] = 9'h100; //   Start column [15:8]
        init_sequence[7'h5a] = 9'h100; //   Start column [7:0]
        init_sequence[7'h5b] = 9'h100; //   End column [15:8]
        init_sequence[7'h5c] = 9'h1ef; //   End column [7:0]
        init_sequence[7'h5d] = 9'h02b; // Page Address Set
        init_sequence[7'h5e] = 9'h100; //   Start position [15:8]
        init_sequence[7'h5f] = 9'h100; //   Start position [7:0]
        init_sequence[7'h60] = 9'h101; //   End position   [15:8]
        init_sequence[7'h61] = 9'h13f; //   End position   [7:0]
        init_sequence[7'h62] = 9'h035; // Tearing Effect Line ON
        init_sequence[7'h63] = 9'h000; //   V-Blanking information only (set to 01h for both V-Blanking and H-Blanking information
        init_sequence[7'h64] = 9'h02c; // Memory Write
        init_sequence[7'h65] = 9'h1ff; // End of sequence
    end

    always @ (posedge i_clk) begin
        // Reset state
        if (state[0] == 1'b1) begin
            state               <= 6'b000001;
            reg_lcd_wr          <= 1'b1;
            reg_lcd_rs          <= 1'b1;
            reg_lcd_data        <= 16'h0000;
            reg_pixel_byte      <= 1'b0;
            reg_pixel_x         <= 0;
            reg_pixel_y         <= 0;
            state <= 8'b0000_0010;
        end

        // Idle state at start
        if (state[1] == 1'b1) begin
            reg_lcd_rs          <= 1'b1;
            reg_lcd_data        <= 16'h0000;
            reg_lcd_wr          <= 1'b1;
            reg_pixel_byte      <= 1'b0;
            state               <= 8'b0000_0100;
        end

        // LCD init state 
        if (state[2] == 1'b1) begin // LCD init state
            reg_pixel_byte <= 1'b0;
            // Put the config byte on the bus
            reg_lcd_rs   <= init_sequence[init_sequence_counter][8];
            reg_lcd_data[15:8] <= 8'h00;
            reg_lcd_data[7:0] <= init_sequence[init_sequence_counter][7:0];
            reg_lcd_wr   <= 1'b0;
            state <= 8'b0000_1000;
        end

        // Latch init byte
        if (state[3] == 1'b1) begin
            init_sequence_counter <= init_sequence_counter + 1;
            reg_lcd_wr <= 1'b1;
            state <= 8'b0000_0100;

            // When done jump to RGB data
            if (init_sequence[init_sequence_counter] == 9'h1ff) begin
                state <= 8'b0001_0000;
                reg_lcd_data <= 16'h00;
                reg_lcd_wr   <= 1'b1;
            end
        end

        // Write the test pattorn to the LCD 
        if (state[4] == 1'b1) begin
            reg_lcd_rs   <= 1'b1;

            // generate test pattern 
            // reg_lcd_data <= 16'b0000000000000000;
            // // Y border
            // if (reg_pixel_y < 16) begin
            //     reg_lcd_data <= 16'b1111_1000_0000_0000;
            // end else begin
            //     if (reg_pixel_x[3:0] == 0) begin
            //         reg_lcd_data <= 16'b0000_0111_1110_0000;
            //     end
            //     if (reg_pixel_y[3:0] == 0) begin
            //         reg_lcd_data <= 16'b0000_0000_0001_1111;
            //     end
            // end

            // Pixel data to output
            reg_lcd_data <= i_pixel_data;

            // keep track of the screen position
            reg_lcd_wr   <= 1'b0;
            reg_pixel_byte <= 1'b0; // Switch to output [7:0]
            state <= 8'b0010_0000;
        end

        // handle first byte latch
        if (state[5] == 1'b1) begin
            reg_lcd_wr   <= 1'b1;
            state <= 8'b0100_0000;
        end

        // handle second byte setup
        if (state[6] == 1'b1) begin
            reg_lcd_wr   <= 1'b0;
            reg_pixel_byte <= 1'b1; // Switch to output [15:8]
            state <= 8'b1000_0000;
        end

        // handle second byte latch
        // And adjust counters
        if (state[7] == 1'b1) begin
            reg_lcd_wr   <= 1'b1;
            // X and Y counters
            reg_pixel_x <= reg_pixel_x + 1;
            // Limit counters
            if (reg_pixel_x == 319) begin
                reg_pixel_x <= 0;
                reg_pixel_y <= reg_pixel_y + 1;
                if (reg_counter == 319) begin
                    reg_counter <= 0;
                end else begin
                    reg_counter <= reg_counter + 1;
                end
            end
            if (reg_pixel_y == 240) begin
                reg_pixel_y <= 0;
            end
            state <= 8'b0001_0000;
        end

        // Reset routine
        // Because of non-blocking assignment this block overrides 
        // previous assignments in the block
        if (i_reset) begin // Reset state
            state <= 8'b0000_0001; // Reset state
        end
    end

    assign o_lcd_wr   = reg_lcd_wr;
    assign o_lcd_rs   = reg_lcd_rs;
    assign o_lcd_data = reg_pixel_byte ? reg_lcd_data[15:8] : reg_lcd_data[7:0];

    // X and Y Position out of the module
    assign o_pixel_x = reg_pixel_x;
    assign o_pixel_y = reg_pixel_y;

endmodule

pc_vga_8x16_80_FF.v
`timescale 1ns / 1ps
`default_nettype none
module pc_vga_8x16_80_FF (
    input  clk,
    input  [6:0] ascii_code,
    input  [3:0] row,
    input  [2:0]  col,
    output reg row_of_pixels
);
    // 2D array 8-bit offset, 6-bit index
    reg [0:255] BRAM_PC_VGA_0 [0:63];

    // Initialize the high character ROM
    // For convenience a hex file is usued 
    initial begin
        $readmemh("./VGA_8x16_80_FF.mem", BRAM_PC_VGA_0);
    end

    // Retrieve the correct pixel value from ROM
    always @(posedge clk) begin
        row_of_pixels <= BRAM_PC_VGA_0[ascii_code[6:1]][{ ascii_code[0], row, ~col}];
    end

endmodule

pc_vga_8x16_00_7F.v
`timescale 1ns / 1ps
`default_nettype none
module pc_vga_8x16_00_7F (
    input  clk,
    input  [6:0] ascii_code,
    input  [3:0] row,
    input  [2:0] col,
    output reg row_of_pixels
);
    // 2D array 8-bit offset, 6-bit index
    reg [0:255] BRAM_PC_VGA_0 [0:63];

    // Initialize the low character rom
    // For convenience a hex file is usued 
    initial begin
        $readmemh("./VGA_8x16_00_7F.mem", BRAM_PC_VGA_0);
    end

    // Retrieve the correct Pixel value from ROM
    always @(posedge clk) begin
        row_of_pixels <= BRAM_PC_VGA_0[ascii_code[6:1]][{ ascii_code[0], row, ~col}];
    end

endmodule

pc_vga_8x16.v
/*
 * This file implements a Character ROM for translating ASCII
 * character codes into 8x16 pixel image.
 *
 * The input to the module is:
 *  1) 8 bit ASCII code,
 *  2) column select, 0..7, which indicates which of the 8 pixels of the character
 *     image will be returned
 *  3) row select, 0..15, which indicates which of the 16 rows of pixels of the character
 *     image will be returned
 */

module pc_vga_8x16 (
    input   clk,
    input [2:0] col,
    input [3:0] row,
    input [7:0] ascii,
    output pixel
);

    wire  pixel_row_00_7f;
    wire  pixel_row_80_ff;

    // Instances
    pc_vga_8x16_00_7F U1 (
        .clk(clk),
        .ascii_code(ascii[6:0]),
        .row(~row),
        .col(~col),
        .row_of_pixels(pixel_row_00_7f)
    );
    pc_vga_8x16_80_FF U2 (
        .clk(clk),
        .ascii_code(ascii[6:0]),
        .row(~row),
        .col(col),
        .row_of_pixels(pixel_row_80_ff)
    );

    assign pixel = ( ascii[7] == 0) ? pixel_row_00_7f : pixel_row_80_ff;

endmodule

simulation_tb.v
`default_nettype none
`define DUMPSTR(x) `"x.vcd`"
`timescale 1 ns / 1 ns

module simulation_tb;
    // Generate the clock
    reg r_clk;

    reg        r_rst;
    wire [7:0] dbout;
    wire       cs;
    wire       rest;
    wire       rs;
    wire       wr;
    wire       rd;
    wire       aled;

    // clock_gen clock_gen_sim (
    //     .enable(1'b1),
    //     .clk(r_clk)
    // );

    initial begin
        r_clk = 1'b0;
    end

    always begin
        #5 r_clk = !r_clk;
    end



    initial begin
        $timeformat(3, 2, " ns", 20);
    end

    reg [9:0] r_count;

    initial begin
        r_rst = 1'b1;
        r_count = 0;
    end

    always @(posedge r_clk) begin
        r_count <= r_count + 1;

        if (r_count == 'h10) begin
            r_rst <= 1'b0;
        end
    end

    // LCD test string
    reg [7:0] r_lcd_test_string [0:40];
    initial begin
        r_lcd_test_string[0] = "a";
        r_lcd_test_string[1] = "b";
        r_lcd_test_string[2] = "c";
        r_lcd_test_string[3] = "d";
        r_lcd_test_string[4] = "e";
        r_lcd_test_string[5] = "f";
        r_lcd_test_string[6] = "g";
        r_lcd_test_string[7] = "h";
        r_lcd_test_string[8] = "i";
        r_lcd_test_string[9] = "j";
        r_lcd_test_string[10] = "k";
        r_lcd_test_string[11] = "l";
        r_lcd_test_string[12] = "m";
        r_lcd_test_string[13] = "n";
        r_lcd_test_string[14] = "o";
        r_lcd_test_string[15] = "p";
        r_lcd_test_string[15] = "q";
    end

    // Character ROM
    wire [8:0] pos_x;
    wire [7:0] pos_y;
    wire [2:0] char_col = 0;
    wire [3:0] char_row = 0;
    wire [7:0] char_ascii = 0;
    wire       pixel;
    pc_vga_8x16 my_char_rom (
        .clk(r_clk),
        .col(pos_x[2:0]),
        .row(pos_y[3:0]),
        .ascii(r_lcd_test_string[pos_x[8:3]]),
        .pixel(pixel)
    );

    // LCD code
    lcd my_lcd(
        .i_clk(r_clk),
        .i_reset(r_rst),
        .o_lcd_data(dbout),
        .o_lcd_rs(rs),
        .o_lcd_wr(wr),
        .i_pixel_data(pixel ? 16'hffff : 16'h0000),
        .o_pixel_x(pos_x),
        .o_pixel_y(pos_y),
        .i_lcd_fmark()
    );

    // Print character start
    // always @(posedge r_clk) begin
    //     if (r_pixel_p_x != pixel_x && pixel_x < 128) begin
    //         if (pixel_x[2:0] == 0) begin
    //             $write(":");
    //             p_x = 1'b1;
    //         end
    //     end
    // end

    // Print the output in pixels to the terminal
    reg [8:0] r_pos_p_x;
    reg [7:0] r_pos_p_y;
    reg       p_x = 0;
    reg       p_y = 0;
    always @(posedge r_clk) begin
        p_x <= 1'b0;
        p_y <= 1'b0;
        r_pos_p_x <= pos_x;
        r_pos_p_y <= pos_y;

        if (r_pos_p_x != pos_x) begin
            p_x <= 1'b1;
        end

        if (pos_x[2:0] == 3'b000 && p_x) begin
            $write("|");
        end

        if (p_x && pos_x < 128) begin

            if (pixel) begin
                $write("#");
            end else begin
                $write(" ");
            end
        end

        if (r_pos_p_y != pos_y) begin
            $write("||\n");
            p_y <= 1'b1;
            if (pos_y[3:0] == 0) begin
                $write("------------------------------------------------------------------------------\n");
            end
        end

    end

    initial begin
        $dumpfile(`DUMPSTR(`VCD_OUTPUT)); // Dump the VCD file 
        $dumpvars(0, simulation_tb);

        $display("Simulation started");
        repeat (40000) @(posedge r_clk);
        // End the simulation when we reach stage
        // if (ili9341sim.stateonehot[2] == 1'b1 || r_count == 'hFF) begin
        $display("Simulation finished");
        $finish;
        // end
    end
endmodule

simulation_tb.vcd
$date
	Fri Apr 15 19:31:45 2022
$end
$version
	Icarus Verilog
$end
$timescale
	1ps
$end
$scope module simulation_tb $end
$var wire 8 ! char_ascii [7:0] $end
$var wire 3 " char_col [2:0] $end
$var wire 4 # char_row [3:0] $end
$var wire 1 $ wr $end
$var wire 1 % rs $end
$var wire 8 & pos_y [7:0] $end
$var wire 9 ' pos_x [8:0] $end
$var wire 1 ( pixel $end
$var wire 8 ) dbout [7:0] $end
$var reg 1 * p_x $end
$var reg 1 + p_y $end
$var reg 1 , r_clk $end
$var reg 10 - r_count [9:0] $end
$var reg 9 . r_pos_p_x [8:0] $end
$var reg 8 / r_pos_p_y [7:0] $end
$var reg 1 0 r_rst $end
$scope module my_char_rom $end
$var wire 8 1 ascii [7:0] $end
$var wire 1 , clk $end
$var wire 3 2 col [2:0] $end
$var wire 4 3 row [3:0] $end
$var wire 1 4 pixel_row_80_ff $end
$var wire 1 5 pixel_row_00_7f $end
$var wire 1 ( pixel $end
$scope module U1 $end
$var wire 7 6 ascii_code [6:0] $end
$var wire 1 , clk $end
$var wire 3 7 col [2:0] $end
$var wire 4 8 row [3:0] $end
$var reg 1 5 row_of_pixels $end
$upscope $end
$scope module U2 $end
$var wire 7 9 ascii_code [6:0] $end
$var wire 1 , clk $end
$var wire 3 : col [2:0] $end
$var wire 4 ; row [3:0] $end
$var reg 1 4 row_of_pixels $end
$upscope $end
$upscope $end
$scope module my_lcd $end
$var wire 1 , i_clk $end
$var wire 1 < i_lcd_fmark $end
$var wire 16 = i_pixel_data [15:0] $end
$var wire 1 0 i_reset $end
$var wire 1 % o_lcd_rs $end
$var wire 1 $ o_lcd_wr $end
$var wire 8 > o_pixel_y [7:0] $end
$var wire 9 ? o_pixel_x [8:0] $end
$var wire 8 @ o_lcd_data [7:0] $end
$var reg 7 A init_sequence_counter [6:0] $end
$var reg 9 B reg_counter [8:0] $end
$var reg 16 C reg_lcd_data [15:0] $end
$var reg 1 D reg_lcd_rs $end
$var reg 1 E reg_lcd_wr $end
$var reg 1 F reg_pixel_byte $end
$var reg 9 G reg_pixel_x [8:0] $end
$var reg 8 H reg_pixel_y [7:0] $end
$var reg 8 I state [7:0] $end
$upscope $end
$upscope $end
$enddefinitions $end
#0
$dumpvars
b1 I
b0 H
b0 G
0F
1E
1D
b0 C
b0 B
b0 A
b0 @
b0 ?
b0 >
bx =
z<
b1111 ;
b0 :
b1100001 9
b1111 8
b111 7
b1100001 6
x5
x4
b0 3
b0 2
b1100001 1
10
bx /
bx .
b0 -
0,
0+
0*
b0 )
x(
b0 '
b0 &
1%
1$
b0 #
b0 "
b0 !
$end
#5000
b0 =
0(
05
04
b1 I
b1 -
b0 /
b0 .
1,
#10000
0,
#15000
b10 -
b1 I
1,
#20000
0,
#25000
b1 I
b11 -
1,
#30000
0,
#35000
b100 -
b1 I
1,
#40000
0,
#45000
b1 I
b101 -
1,
#50000
0,
#55000
b110 -
b1 I
1,
#60000
0,
#65000
b1 I
b111 -
1,
#70000
0,
#75000
b1000 -
b1 I
1,
#80000
0,
#85000
b1 I
b1001 -
1,
#90000
0,
#95000
b1010 -
b1 I
1,
#100000
0,
#105000
b1 I
b1011 -
1,
#110000
0,
#115000
b1100 -
b1 I
1,
#120000
0,
#125000
b1 I
b1101 -
1,
#130000
0,
#135000
b1110 -
b1 I
1,
#140000
0,
#145000
b1 I
b1111 -
1,
#150000
0,
#155000
b10000 -
b1 I
1,
#160000
0,
#165000
b1 I
00
b10001 -
1,
#170000
0,
#175000
b10010 -
b10 I
1,
#180000
0,
#185000
b100 I
b10011 -
1,
#190000
0,
#195000
b11101111 )
b11101111 @
b10100 -
b1000 I
0$
0E
b11101111 C
0%
0D
1,
#200000
0,
#205000
b100 I
1$
1E
b1 A
b10101 -
1,
#210000
0,
#215000
b11 )
b11 @
b10110 -
b1000 I
0$
0E
b11 C
1%
1D
1,
#220000
0,
#225000
b100 I
1$
1E
b10 A
b10111 -
1,
#230000
0,
#235000
b10000000 )
b10000000 @
b11000 -
b1000 I
0$
0E
b10000000 C
1,
#240000
0,
#245000
b100 I
1$
1E
b11 A
b11001 -
1,
#250000
0,
#255000
b10 )
b10 @
b11010 -
b1000 I
0$
0E
b10 C
1,
#260000
0,
#265000
b100 I
1$
1E
b100 A
b11011 -
1,
#270000
0,
#275000
b11001111 )
b11001111 @
b11100 -
b1000 I
0$
0E
b11001111 C
0%
0D
1,
#280000
0,
#285000
b100 I
1$
1E
b101 A
b11101 -
1,
#290000
0,
#295000
b0 )
b0 @
b11110 -
b1000 I
0$
0E
b0 C
1%
1D
1,
#300000
0,
#305000
b100 I
1$
1E
b110 A
b11111 -
1,
#310000
0,
#315000
b11000001 )
b11000001 @
b100000 -
b1000 I
0$
0E
b11000001 C
1,
#320000
0,
#325000
b100 I
1$
1E
b111 A
b100001 -
1,
#330000
0,
#335000
b110000 )
b110000 @
b100010 -
b1000 I
0$
0E
b110000 C
1,
#340000
0,
#345000
b100 I
1$
1E
b1000 A
b100011 -
1,
#350000
0,
#355000
b11101101 )
b11101101 @
b100100 -
b1000 I
0$
0E
b11101101 C
0%
0D
1,
#360000
0,
#365000
b100 I
1$
1E
b1001 A
b100101 -
1,
#370000
0,
#375000
b1100100 )
b1100100 @
b100110 -
b1000 I
0$
0E
b1100100 C
1%
1D
1,
#380000
0,
#385000
b100 I
1$
1E
b1010 A
b100111 -
1,
#390000
0,
#395000
b11 )
b11 @
b101000 -
b1000 I
0$
0E
b11 C
1,
#400000
0,
#405000
b100 I
1$
1E
b1011 A
b101001 -
1,
#410000
0,
#415000
b10010 )
b10010 @
b101010 -
b1000 I
0$
0E
b10010 C
1,
#420000
0,
#425000
b100 I
1$
1E
b1100 A
b101011 -
1,
#430000
0,
#435000
b10000001 )
b10000001 @
b101100 -
b1000 I
0$
0E
b10000001 C
1,
#440000
0,
#445000
b100 I
1$
1E
b1101 A
b101101 -
1,
#450000
0,
#455000
b11101000 )
b11101000 @
b101110 -
b1000 I
0$
0E
b11101000 C
0%
0D
1,
#460000
0,
#465000
b100 I
1$
1E
b1110 A
b101111 -
1,
#470000
0,
#475000
b10000101 )
b10000101 @
b110000 -
b1000 I
0$
0E
b10000101 C
1%
1D
1,
#480000
0,
#485000
b100 I
1$
1E
b1111 A
b110001 -
1,
#490000
0,
#495000
b0 )
b0 @
b110010 -
b1000 I
0$
0E
b0 C
1,
#500000
0,
#505000
b100 I
1$
1E
b10000 A
b110011 -
1,
#510000
0,
#515000
b1111000 )
b1111000 @
b110100 -
b1000 I
0$
0E
b1111000 C
1,
#520000
0,
#525000
b100 I
1$
1E
b10001 A
b110101 -
1,
#530000
0,
#535000
b11001011 )
b11001011 @
b110110 -
b1000 I
0$
0E
b11001011 C
0%
0D
1,
#540000
0,
#545000
b100 I
1$
1E
b10010 A
b110111 -
1,
#550000
0,
#555000
b111001 )
b111001 @
b111000 -
b1000 I
0$
0E
b111001 C
1%
1D
1,
#560000
0,
#565000
b100 I
1$
1E
b10011 A
b111001 -
1,
#570000
0,
#575000
b101100 )
b101100 @
b111010 -
b1000 I
0$
0E
b101100 C
1,
#580000
0,
#585000
b100 I
1$
1E
b10100 A
b111011 -
1,
#590000
0,
#595000
b0 )
b0 @
b111100 -
b1000 I
0$
0E
b0 C
1,
#600000
0,
#605000
b100 I
1$
1E
b10101 A
b111101 -
1,
#610000
0,
#615000
b110100 )
b110100 @
b111110 -
b1000 I
0$
0E
b110100 C
1,
#620000
0,
#625000
b100 I
1$
1E
b10110 A
b111111 -
1,
#630000
0,
#635000
b10 )
b10 @
b1000000 -
b1000 I
0$
0E
b10 C
1,
#640000
0,
#645000
b100 I
1$
1E
b10111 A
b1000001 -
1,
#650000
0,
#655000
b11110111 )
b11110111 @
b1000010 -
b1000 I
0$
0E
b11110111 C
0%
0D
1,
#660000
0,
#665000
b100 I
1$
1E
b11000 A
b1000011 -
1,
#670000
0,
#675000
b100000 )
b100000 @
b1000100 -
b1000 I
0$
0E
b100000 C
1%
1D
1,
#680000
0,
#685000
b100 I
1$
1E
b11001 A
b1000101 -
1,
#690000
0,
#695000
b11101010 )
b11101010 @
b1000110 -
b1000 I
0$
0E
b11101010 C
0%
0D
1,
#700000
0,
#705000
b100 I
1$
1E
b11010 A
b1000111 -
1,
#710000
0,
#715000
b0 )
b0 @
b1001000 -
b1000 I
0$
0E
b0 C
1%
1D
1,
#720000
0,
#725000
b100 I
1$
1E
b11011 A
b1001001 -
1,
#730000
0,
#735000
b1001010 -
b1000 I
0$
0E
1,
#740000
0,
#745000
b100 I
1$
1E
b11100 A
b1001011 -
1,
#750000
0,
#755000
b11000000 )
b11000000 @
b1001100 -
b1000 I
0$
0E
b11000000 C
0%
0D
1,
#760000
0,
#765000
b100 I
1$
1E
b11101 A
b1001101 -
1,
#770000
0,
#775000
b100011 )
b100011 @
b1001110 -
b1000 I
0$
0E
b100011 C
1%
1D
1,
#780000
0,
#785000
b100 I
1$
1E
b11110 A
b1001111 -
1,
#790000
0,
#795000
b11000001 )
b11000001 @
b1010000 -
b1000 I
0$
0E
b11000001 C
0%
0D
1,
#800000
0,
#805000
b100 I
1$
1E
b11111 A
b1010001 -
1,
#810000
0,
#815000
b10000 )
b10000 @
b1010010 -
b1000 I
0$
0E
b10000 C
1%
1D
1,
#820000
0,
#825000
b100 I
1$
1E
b100000 A
b1010011 -
1,
#830000
0,
#835000
b11000101 )
b11000101 @
b1010100 -
b1000 I
0$
0E
b11000101 C
0%
0D
1,
#840000
0,
#845000
b100 I
1$
1E
b100001 A
b1010101 -
1,
#850000
0,
#855000
b111110 )
b111110 @
b1010110 -
b1000 I
0$
0E
b111110 C
1%
1D
1,
#860000
0,
#865000
b100 I
1$
1E
b100010 A
b1010111 -
1,
#870000
0,
#875000
b101000 )
b101000 @
b1011000 -
b1000 I
0$
0E
b101000 C
1,
#880000
0,
#885000
b100 I
1$
1E
b100011 A
b1011001 -
1,
#890000
0,
#895000
b11000111 )
b11000111 @
b1011010 -
b1000 I
0$
0E
b11000111 C
0%
0D
1,
#900000
0,
#905000
b100 I
1$
1E
b100100 A
b1011011 -
1,
#910000
0,
#915000
b10000110 )
b10000110 @
b1011100 -
b1000 I
0$
0E
b10000110 C
1%
1D
1,
#920000
0,
#925000
b100 I
1$
1E
b100101 A
b1011101 -
1,
#930000
0,
#935000
b110110 )
b110110 @
b1011110 -
b1000 I
0$
0E
b110110 C
0%
0D
1,
#940000
0,
#945000
b100 I
1$
1E
b100110 A
b1011111 -
1,
#950000
0,
#955000
b1001000 )
b1001000 @
b1100000 -
b1000 I
0$
0E
b1001000 C
1%
1D
1,
#960000
0,
#965000
b100 I
1$
1E
b100111 A
b1100001 -
1,
#970000
0,
#975000
b111010 )
b111010 @
b1100010 -
b1000 I
0$
0E
b111010 C
0%
0D
1,
#980000
0,
#985000
b100 I
1$
1E
b101000 A
b1100011 -
1,
#990000
0,
#995000
b1010101 )
b1010101 @
b1100100 -
b1000 I
0$
0E
b1010101 C
1%
1D
1,
#1000000
0,
#1005000
b100 I
1$
1E
b101001 A
b1100101 -
1,
#1010000
0,
#1015000
b10110001 )
b10110001 @
b1100110 -
b1000 I
0$
0E
b10110001 C
0%
0D
1,
#1020000
0,
#1025000
b100 I
1$
1E
b101010 A
b1100111 -
1,
#1030000
0,
#1035000
b0 )
b0 @
b1101000 -
b1000 I
0$
0E
b0 C
1%
1D
1,
#1040000
0,
#1045000
b100 I
1$
1E
b101011 A
b1101001 -
1,
#1050000
0,
#1055000
b11000 )
b11000 @
b1101010 -
b1000 I
0$
0E
b11000 C
1,
#1060000
0,
#1065000
b100 I
1$
1E
b101100 A
b1101011 -
1,
#1070000
0,
#1075000
b10110110 )
b10110110 @
b1101100 -
b1000 I
0$
0E
b10110110 C
0%
0D
1,
#1080000
0,
#1085000
b100 I
1$
1E
b101101 A
b1101101 -
1,
#1090000
0,
#1095000
b1000 )
b1000 @
b1101110 -
b1000 I
0$
0E
b1000 C
1%
1D
1,
#1100000
0,
#1105000
b100 I
1$
1E
b101110 A
b1101111 -
1,
#1110000
0,
#1115000
b10000010 )
b10000010 @
b1110000 -
b1000 I
0$
0E
b10000010 C
1,
#1120000
0,
#1125000
b100 I
1$
1E
b101111 A
b1110001 -
1,
#1130000
0,
#1135000
b100111 )
b100111 @
b1110010 -
b1000 I
0$
0E
b100111 C
1,
#1140000
0,
#1145000
b100 I
1$
1E
b110000 A
b1110011 -
1,
#1150000
0,
#1155000
b11110010 )
b11110010 @
b1110100 -
b1000 I
0$
0E
b11110010 C
0%
0D
1,
#1160000
0,
#1165000
b100 I
1$
1E
b110001 A
b1110101 -
1,
#1170000
0,
#1175000
b0 )
b0 @
b1110110 -
b1000 I
0$
0E
b0 C
1%
1D
1,
#1180000
0,
#1185000
b100 I
1$
1E
b110010 A
b1110111 -
1,
#1190000
0,
#1195000
b100110 )
b100110 @
b1111000 -
b1000 I
0$
0E
b100110 C
0%
0D
1,
#1200000
0,
#1205000
b100 I
1$
1E
b110011 A
b1111001 -
1,
#1210000
0,
#1215000
b1 )
b1 @
b1111010 -
b1000 I
0$
0E
b1 C
1%
1D
1,
#1220000
0,
#1225000
b100 I
1$
1E
b110100 A
b1111011 -
1,
#1230000
0,
#1235000
b11100000 )
b11100000 @
b1111100 -
b1000 I
0$
0E
b11100000 C
0%
0D
1,
#1240000
0,
#1245000
b100 I
1$
1E
b110101 A
b1111101 -
1,
#1250000
0,
#1255000
b1111 )
b1111 @
b1111110 -
b1000 I
0$
0E
b1111 C
1%
1D
1,
#1260000
0,
#1265000
b100 I
1$
1E
b110110 A
b1111111 -
1,
#1270000
0,
#1275000
b110001 )
b110001 @
b10000000 -
b1000 I
0$
0E
b110001 C
1,
#1280000
0,
#1285000
b100 I
1$
1E
b110111 A
b10000001 -
1,
#1290000
0,
#1295000
b101011 )
b101011 @
b10000010 -
b1000 I
0$
0E
b101011 C
1,
#1300000
0,
#1305000
b100 I
1$
1E
b111000 A
b10000011 -
1,
#1310000
0,
#1315000
b1100 )
b1100 @
b10000100 -
b1000 I
0$
0E
b1100 C
1,
#1320000
0,
#1325000
b100 I
1$
1E
b111001 A
b10000101 -
1,
#1330000
0,
#1335000
b1110 )
b1110 @
b10000110 -
b1000 I
0$
0E
b1110 C
1,
#1340000
0,
#1345000
b100 I
1$
1E
b111010 A
b10000111 -
1,
#1350000
0,
#1355000
b1000 )
b1000 @
b10001000 -
b1000 I
0$
0E
b1000 C
1,
#1360000
0,
#1365000
b100 I
1$
1E
b111011 A
b10001001 -
1,
#1370000
0,
#1375000
b1001110 )
b1001110 @
b10001010 -
b1000 I
0$
0E
b1001110 C
1,
#1380000
0,
#1385000
b100 I
1$
1E
b111100 A
b10001011 -
1,
#1390000
0,
#1395000
b11110001 )
b11110001 @
b10001100 -
b1000 I
0$
0E
b11110001 C
1,
#1400000
0,
#1405000
b100 I
1$
1E
b111101 A
b10001101 -
1,
#1410000
0,
