lcd.v

`default_nettype none

module lcd (
    input            i_clk,
    input            i_reset,
    output     [7:0] o_lcd_data,
    output           o_lcd_rs,
    output           o_lcd_wr,
    input            i_lcd_fmark // Unused for now
);

    reg reg_lcd_wr = 1'b1;
    reg reg_lcd_rs = 1'b1;
    reg [15:0] reg_lcd_data = 16'h0000;
    reg reg_pixel_byte = 1'b0;
    reg reg_pixel_byte_next = 1'b0;
    reg finish_init = 1'b0;
    reg [8:0] reg_pixel_x = 0;
    reg [7:0] reg_pixel_y = 0;
    reg [8:0] reg_counter = 0;

    reg [7:0] state = 8'b0000_0001;

    // ILI9431 initialization sequence
    reg [6:0] init_sequence_counter = 0;
    reg [8:0] init_sequence[0:100];

    initial begin
        init_sequence[7'h00] = 9'h0ef;
        init_sequence[7'h01] = 9'h103;
        init_sequence[7'h02] = 9'h180;
        init_sequence[7'h03] = 9'h102;
        init_sequence[7'h04] = 9'h0cf; // Power control B
        init_sequence[7'h05] = 9'h100;
        init_sequence[7'h06] = 9'h1c1;
        init_sequence[7'h07] = 9'h130;
        init_sequence[7'h08] = 9'h0ed; // Power on sequence control
        init_sequence[7'h09] = 9'h164;
        init_sequence[7'h0a] = 9'h103;
        init_sequence[7'h0b] = 9'h112;
        init_sequence[7'h0c] = 9'h181;
        init_sequence[7'h0d] = 9'h0e8; // Driver timing control A
        init_sequence[7'h0e] = 9'h185;
        init_sequence[7'h0f] = 9'h100;
        init_sequence[7'h10] = 9'h178;
        init_sequence[7'h11] = 9'h0cb; // Power control A
        init_sequence[7'h12] = 9'h139;
        init_sequence[7'h13] = 9'h12c;
        init_sequence[7'h14] = 9'h100;
        init_sequence[7'h15] = 9'h134;
        init_sequence[7'h16] = 9'h102;
        init_sequence[7'h17] = 9'h0f7; // Pump ratio control
        init_sequence[7'h18] = 9'h120;
        init_sequence[7'h19] = 9'h0ea; // Driver timing control B
        init_sequence[7'h1a] = 9'h100;
        init_sequence[7'h1b] = 9'h100;
        init_sequence[7'h1c] = 9'h0c0; // Power control 1
        init_sequence[7'h1d] = 9'h123;
        init_sequence[7'h1e] = 9'h0c1; // Power control 2
        init_sequence[7'h1f] = 9'h110;
        init_sequence[7'h20] = 9'h0c5; // VCOM Control 1
        init_sequence[7'h21] = 9'h13e;
        init_sequence[7'h22] = 9'h128;
        init_sequence[7'h23] = 9'h0c7; // VCOM Control 2
        init_sequence[7'h24] = 9'h186;
        init_sequence[7'h25] = 9'h036; // Memory Access Control
        init_sequence[7'h26] = 9'h148;
        init_sequence[7'h27] = 9'h03a;
        init_sequence[7'h28] = 9'h155;
        init_sequence[7'h29] = 9'h0b1;
        init_sequence[7'h2a] = 9'h100;
        init_sequence[7'h2b] = 9'h118;
        init_sequence[7'h2c] = 9'h0b6;
        init_sequence[7'h2d] = 9'h108;
        init_sequence[7'h2e] = 9'h182;
        init_sequence[7'h2f] = 9'h127;
        init_sequence[7'h30] = 9'h0f2;
        init_sequence[7'h31] = 9'h100;
        init_sequence[7'h32] = 9'h026;
        init_sequence[7'h33] = 9'h101;
        init_sequence[7'h34] = 9'h0e0;
        init_sequence[7'h35] = 9'h10f;
        init_sequence[7'h36] = 9'h131;
        init_sequence[7'h37] = 9'h12b;
        init_sequence[7'h38] = 9'h10c;
        init_sequence[7'h39] = 9'h10e;
        init_sequence[7'h3a] = 9'h108;
        init_sequence[7'h3b] = 9'h14e;
        init_sequence[7'h3c] = 9'h1f1;
        init_sequence[7'h3d] = 9'h137;
        init_sequence[7'h3e] = 9'h107;
        init_sequence[7'h3f] = 9'h110;
        init_sequence[7'h40] = 9'h103;
        init_sequence[7'h41] = 9'h10e;
        init_sequence[7'h42] = 9'h109;
        init_sequence[7'h43] = 9'h100;
        init_sequence[7'h44] = 9'h0e1;
        init_sequence[7'h45] = 9'h100;
        init_sequence[7'h46] = 9'h10e;
        init_sequence[7'h47] = 9'h114;
        init_sequence[7'h48] = 9'h103;
        init_sequence[7'h49] = 9'h111;
        init_sequence[7'h4a] = 9'h107;
        init_sequence[7'h4b] = 9'h131;
        init_sequence[7'h4c] = 9'h1c1;
        init_sequence[7'h4d] = 9'h148;
        init_sequence[7'h4e] = 9'h108;
        init_sequence[7'h4f] = 9'h10f;
        init_sequence[7'h50] = 9'h10c;
        init_sequence[7'h51] = 9'h131;
        init_sequence[7'h52] = 9'h136;
        init_sequence[7'h53] = 9'h10f;
        init_sequence[7'h54] = 9'h011; // Sleep Out
        init_sequence[7'h55] = 9'h029; // Display ON
        init_sequence[7'h56] = 9'h036; // Memory Access Control
        init_sequence[7'h57] = 9'h108; //   Select BGR color filter, per LCD different color sequence
        init_sequence[7'h58] = 9'h02a; // Column Address Set
        init_sequence[7'h59] = 9'h100; //   Start column [15:8]
        init_sequence[7'h5a] = 9'h100; //   Start column [7:0]
        init_sequence[7'h5b] = 9'h100; //   End column [15:8]
        init_sequence[7'h5c] = 9'h1ef; //   End column [7:0]
        init_sequence[7'h5d] = 9'h02b; // Page Address Set
        init_sequence[7'h5e] = 9'h100; //   Start position [15:8]
        init_sequence[7'h5f] = 9'h100; //   Start position [7:0]
        init_sequence[7'h60] = 9'h101; //   End position   [15:8]
        init_sequence[7'h61] = 9'h13f; //   End position   [7:0]
        init_sequence[7'h62] = 9'h035; // Tearing Effect Line ON
        init_sequence[7'h63] = 9'h000; //   V-Blanking information only (set to 01h for both V-Blanking and H-Blanking information
        init_sequence[7'h64] = 9'h02c; // Memory Write
    end

    always @ (posedge i_clk) begin
        // Reset state
        if (state[0] == 1'b1) begin
            state               <= 6'b000001;
            reg_lcd_wr          <= 1'b1;
            reg_lcd_rs          <= 1'b1;
            reg_lcd_data        <= 16'h0000;
            reg_pixel_byte      <= 1'b0;
            reg_pixel_byte_next <= 1'b0;
            reg_pixel_x         <= 0;
            reg_pixel_y         <= 0;
            state <= 8'b0000_0010;
        end

        // Idle state at start
        if (state[1] == 1'b1) begin
            reg_lcd_rs          <= 1'b1;
            reg_lcd_data        <= 16'h0000;
            reg_lcd_wr          <= 1'b1;
            reg_pixel_byte      <= 1'b0;
            reg_pixel_byte_next <= 1'b0;
            state               <= 8'b0000_0100;
        end

        // LCD init state 
        if (state[2] == 1'b1) begin // LCD init state
            reg_pixel_byte <= 1'b0;
            reg_pixel_byte_next <= 1'b0;
            // Put the config byte on the bus
            reg_lcd_rs   <= init_sequence[init_sequence_counter][8];
            reg_lcd_data[15:8] <= 8'h00;
            reg_lcd_data[7:0] <= init_sequence[init_sequence_counter][7:0];
            reg_lcd_wr   <= 1'b0;
            state <= 8'b0000_1000;

            // When done jump to RGB data
            if (init_sequence_counter == 100) begin
                state <= 8'b0001_0000;
                reg_lcd_data <= 16'h00;
                reg_lcd_wr   <= 1'b1;
            end
        end

        // Latch init byte
        if (state[3] == 1'b1) begin
            init_sequence_counter <= init_sequence_counter + 1;
            reg_lcd_wr <= 1'b1;
            state <= 8'b0000_0100;
        end

        // Write the test pattorn to the LCD 
        if (state[4] == 1'b1) begin
            reg_lcd_rs   <= 1'b1;

            // generate test pattern 
            reg_lcd_data <= 16'b0000000000000000;
            // Y border
            if (reg_pixel_y < 16) begin
                reg_lcd_data <= 16'b1111_1000_0000_0000;
            end else begin
                // reg_lcd_data <= 16'b0000011111100000;
                // reg_lcd_data <= {!reg_pixel_x[8:4], reg_pixel_y[7:2], reg_pixel_x[8:4]};
                if (reg_pixel_x[3:0] == 0) begin
                    reg_lcd_data <= 16'b0000_0111_1110_0000;
                end
                if (reg_pixel_y[3:0] == 0) begin
                    reg_lcd_data <= 16'h0000_0000_0001_1111;
                end
            end

            // keep track of the screen position
            reg_lcd_wr   <= 1'b0;
            reg_pixel_byte <= 1'b0; // Switch to output [7:0]
            state <= 8'b0010_0000;
        end

        // handle first byte latch
        if (state[5] == 1'b1) begin
            reg_lcd_wr   <= 1'b1;
            state <= 8'b0100_0000;
        end

        // handle second byte setup
        if (state[6] == 1'b1) begin
            reg_lcd_wr   <= 1'b0;
            reg_pixel_byte <= 1'b1; // Switch to output [15:8]
            state <= 8'b1000_0000;
        end

        // handle second byte latch
        // And adjust counters
        if (state[7] == 1'b1) begin
            reg_lcd_wr   <= 1'b1;
            // X and Y counters
            reg_pixel_x <= reg_pixel_x + 1;
            // Limit counters
            if (reg_pixel_x == 319) begin
                reg_pixel_x <= 0;
                reg_pixel_y <= reg_pixel_y + 1;
                if (reg_counter == 319) begin
                    reg_counter <= 0;
                end else begin
                    reg_counter <= reg_counter + 1;
                end
            end
            if (reg_pixel_y == 240) begin
                reg_pixel_y <= 0;
            end
            state <= 8'b0001_0000;
        end

        // Reset routine
        // Because of non-blocking assignment this block overrides 
        // previous assignments in the block
        if (i_reset) begin // Reset state
            state <= 8'b0000_0001; // Reset state
        end
    end

    assign o_lcd_wr   = reg_lcd_wr;
    assign o_lcd_rs   = reg_lcd_rs;
    assign o_lcd_data = reg_pixel_byte ? reg_lcd_data[15:8] : reg_lcd_data[7:0];

endmodule

simulation_tb.v
`default_nettype none
`define DUMPSTR(x) `"x.vcd`"
`timescale 1 ns / 1 ns

module simulation_tb;
    // Generate the clock
    reg r_clk;

    reg        r_rst;
    wire [7:0] dbout;
    wire       cs;
    wire       rest;
    wire       rs;
    wire       wr;
    wire       rd;
    wire       aled;

    // clock_gen clock_gen_sim (
    //     .enable(1'b1),
    //     .clk(r_clk)
    // );

    initial begin
        r_clk = 1'b0;
    end

    always begin
        #5 r_clk = !r_clk;
    end



    initial begin
        $timeformat(3, 2, " ns", 20);
    end

    reg [9:0] r_count;

    initial begin
        r_rst = 1'b1;
        r_count = 0;
    end

    always @(posedge r_clk) begin
        r_count <= r_count + 1;

        if (r_count == 'h10) begin
            r_rst <= 1'b0;
        end
    end

    // ili9341 #(

    // ) ili9341sim (
    //     .clk(r_clk),
    //     .rst(r_rst),
    //     .dbout(dbout),
    //     .cs(cs),
    //     .rest(rest),
    //     .rs(rs),
    //     .wr(wr),
    //     .rd(rd)
    // );

    lcd my_lcd(
        .i_clk(r_clk),
        .i_reset(r_rst),
        .o_lcd_data(dbout),
        .o_lcd_rs(rs),
        .o_lcd_wr(wr),
        .i_lcd_fmark()
    );


    initial begin
        $dumpfile(`DUMPSTR(`VCD_OUTPUT)); // Dump the VCD file
        $dumpvars(0, simulation_tb);

        $display("Simulation started");
        repeat (10000) @(posedge r_clk);
        // End the simulation when we reach stage
        // if (ili9341sim.stateonehot[2] == 1'b1 || r_count == 'hFF) begin
        $display("Simulation finished");
        $finish;
        // end
    end
endmodule

simulation_tb.vcd
$date
	Tue Mar 29 09:09:53 2022
$end
$version
	Icarus Verilog
$end
$timescale
	1ps
$end
$scope module simulation_tb $end
$var wire 1 ! wr $end
$var wire 1 " rs $end
$var wire 8 # dbout [7:0] $end
$var reg 1 $ r_clk $end
$var reg 10 % r_count [9:0] $end
$var reg 1 & r_rst $end
$scope module my_lcd $end
$var wire 1 $ i_clk $end
$var wire 1 ' i_lcd_fmark $end
$var wire 1 & i_reset $end
$var wire 1 " o_lcd_rs $end
$var wire 1 ! o_lcd_wr $end
$var wire 8 ( o_lcd_data [7:0] $end
$var reg 1 ) finish_init $end
$var reg 7 * init_sequence_counter [6:0] $end
$var reg 9 + reg_counter [8:0] $end
$var reg 16 , reg_lcd_data [15:0] $end
$var reg 1 - reg_lcd_rs $end
$var reg 1 . reg_lcd_wr $end
$var reg 1 / reg_pixel_byte $end
$var reg 1 0 reg_pixel_byte_next $end
$var reg 9 1 reg_pixel_x [8:0] $end
$var reg 8 2 reg_pixel_y [7:0] $end
$var reg 8 3 state [7:0] $end
$upscope $end
$upscope $end
$enddefinitions $end
#0
$dumpvars
b1 3
b0 2
b0 1
00
0/
1.
1-
b0 ,
b0 +
b0 *
0)
b0 (
z'
1&
b0 %
0$
b0 #
1"
1!
$end
#5000
b1 3
b1 %
1$
#10000
0$
#15000
b10 %
b1 3
1$
#20000
0$
#25000
b1 3
b11 %
1$
#30000
0$
#35000
b100 %
b1 3
1$
#40000
0$
#45000
b1 3
b101 %
1$
#50000
0$
#55000
b110 %
b1 3
1$
#60000
0$
#65000
b1 3
b111 %
1$
#70000
0$
#75000
b1000 %
b1 3
1$
#80000
0$
#85000
b1 3
b1001 %
1$
#90000
0$
#95000
b1010 %
b1 3
1$
#100000
0$
#105000
b1 3
b1011 %
1$
#110000
0$
#115000
b1100 %
b1 3
1$
#120000
0$
#125000
b1 3
b1101 %
1$
#130000
0$
#135000
b1110 %
b1 3
1$
#140000
0$
#145000
b1 3
b1111 %
1$
#150000
0$
#155000
b10000 %
b1 3
1$
#160000
0$
#165000
b1 3
0&
b10001 %
1$
#170000
0$
#175000
b10010 %
b10 3
1$
#180000
0$
#185000
b100 3
b10011 %
1$
#190000
0$
#195000
b11101111 #
b11101111 (
b10100 %
b1000 3
0!
0.
b11101111 ,
0"
0-
1$
#200000
0$
#205000
b100 3
1!
1.
b1 *
b10101 %
1$
#210000
0$
#215000
b11 #
b11 (
b10110 %
b1000 3
0!
0.
b11 ,
1"
1-
1$
#220000
0$
#225000
b100 3
1!
1.
b10 *
b10111 %
1$
#230000
0$
#235000
b10000000 #
b10000000 (
b11000 %
b1000 3
0!
0.
b10000000 ,
1$
#240000
0$
#245000
b100 3
1!
1.
b11 *
b11001 %
1$
#250000
0$
#255000
b10 #
b10 (
b11010 %
b1000 3
0!
0.
b10 ,
1$
#260000
0$
#265000
b100 3
1!
1.
b100 *
b11011 %
1$
#270000
0$
#275000
b11001111 #
b11001111 (
b11100 %
b1000 3
0!
0.
b11001111 ,
0"
0-
1$
#280000
0$
#285000
b100 3
1!
1.
b101 *
b11101 %
1$
#290000
0$
#295000
b0 #
b0 (
b11110 %
b1000 3
0!
0.
b0 ,
1"
1-
1$
#300000
0$
#305000
b100 3
1!
1.
b110 *
b11111 %
1$
#310000
0$
#315000
b11000001 #
b11000001 (
b100000 %
b1000 3
0!
0.
b11000001 ,
1$
#320000
0$
#325000
b100 3
1!
1.
b111 *
b100001 %
1$
#330000
0$
#335000
b110000 #
b110000 (
b100010 %
b1000 3
0!
0.
b110000 ,
1$
#340000
0$
#345000
b100 3
1!
1.
b1000 *
b100011 %
1$
#350000
0$
#355000
b11101101 #
b11101101 (
b100100 %
b1000 3
0!
0.
b11101101 ,
0"
0-
1$
#360000
0$
#365000
b100 3
1!
1.
b1001 *
b100101 %
1$
#370000
0$
#375000
b1100100 #
b1100100 (
b100110 %
b1000 3
0!
0.
b1100100 ,
1"
1-
1$
#380000
0$
#385000
b100 3
1!
1.
b1010 *
b100111 %
1$
#390000
0$
#395000
b11 #
b11 (
b101000 %
b1000 3
0!
0.
b11 ,
1$
#400000
0$
#405000
b100 3
1!
1.
b1011 *
b101001 %
1$
#410000
0$
#415000
b10010 #
b10010 (
b101010 %
b1000 3
0!
0.
b10010 ,
1$
#420000
0$
#425000
b100 3
1!
1.
b1100 *
b101011 %
1$
#430000
0$
#435000
b10000001 #
b10000001 (
b101100 %
b1000 3
0!
0.
b10000001 ,
1$
#440000
0$
#445000
b100 3
1!
1.
b1101 *
b101101 %
1$
#450000
0$
#455000
b11101000 #
b11101000 (
b101110 %
b1000 3
0!
0.
b11101000 ,
0"
0-
1$
#460000
0$
#465000
b100 3
1!
1.
b1110 *
b101111 %
1$
#470000
0$
#475000
b10000101 #
b10000101 (
b110000 %
b1000 3
0!
0.
b10000101 ,
1"
1-
1$
#480000
0$
#485000
b100 3
1!
1.
b1111 *
b110001 %
1$
#490000
0$
#495000
b0 #
b0 (
b110010 %
b1000 3
0!
0.
b0 ,
1$
#500000
0$
#505000
b100 3
1!
1.
b10000 *
b110011 %
1$
#510000
0$
#515000
b1111000 #
b1111000 (
b110100 %
b1000 3
0!
0.
b1111000 ,
1$
#520000
0$
#525000
b100 3
1!
1.
b10001 *
b110101 %
1$
#530000
0$
#535000
b11001011 #
b11001011 (
b110110 %
b1000 3
0!
0.
b11001011 ,
0"
0-
1$
#540000
0$
#545000
b100 3
1!
1.
b10010 *
b110111 %
1$
#550000
0$
#555000
b111001 #
b111001 (
b111000 %
b1000 3
0!
0.
b111001 ,
1"
1-
1$
#560000
0$
#565000
b100 3
1!
1.
b10011 *
b111001 %
1$
#570000
0$
#575000
b101100 #
b101100 (
b111010 %
b1000 3
0!
0.
b101100 ,
1$
#580000
0$
#585000
b100 3
1!
1.
b10100 *
b111011 %
1$
#590000
0$
#595000
b0 #
b0 (
b111100 %
b1000 3
0!
0.
b0 ,
1$
#600000
0$
#605000
b100 3
1!
1.
b10101 *
b111101 %
1$
#610000
0$
#615000
b110100 #
b110100 (
b111110 %
b1000 3
0!
0.
b110100 ,
1$
#620000
0$
#625000
b100 3
1!
1.
b10110 *
b111111 %
1$
#630000
0$
#635000
b10 #
b10 (
b1000000 %
b1000 3
0!
0.
b10 ,
1$
#640000
0$
#645000
b100 3
1!
1.
b10111 *
b1000001 %
1$
#650000
0$
#655000
b11110111 #
b11110111 (
b1000010 %
b1000 3
0!
0.
b11110111 ,
0"
0-
1$
#660000
0$
#665000
b100 3
1!
1.
b11000 *
b1000011 %
1$
#670000
0$
#675000
b100000 #
b100000 (
b1000100 %
b1000 3
0!
0.
b100000 ,
1"
1-
1$
#680000
0$
#685000
b100 3
1!
1.
b11001 *
b1000101 %
1$
#690000
0$
#695000
b11101010 #
b11101010 (
b1000110 %
b1000 3
0!
0.
b11101010 ,
0"
0-
1$
#700000
0$
#705000
b100 3
1!
1.
b11010 *
b1000111 %
1$
#710000
0$
#715000
b0 #
b0 (
b1001000 %
b1000 3
0!
0.
b0 ,
1"
1-
1$
#720000
0$
#725000
b100 3
1!
1.
b11011 *
b1001001 %
1$
#730000
0$
#735000
b1001010 %
b1000 3
0!
0.
1$
#740000
0$
#745000
b100 3
1!
1.
b11100 *
b1001011 %
1$
#750000
0$
#755000
b11000000 #
b11000000 (
b1001100 %
b1000 3
0!
0.
b11000000 ,
0"
0-
1$
#760000
0$
#765000
b100 3
1!
1.
b11101 *
b1001101 %
1$
#770000
0$
#775000
b100011 #
b100011 (
b1001110 %
b1000 3
0!
0.
b100011 ,
1"
1-
1$
#780000
0$
#785000
b100 3
1!
1.
b11110 *
b1001111 %
1$
#790000
0$
#795000
b11000001 #
b11000001 (
b1010000 %
b1000 3
0!
0.
b11000001 ,
0"
0-
1$
#800000
0$
#805000
b100 3
1!
1.
b11111 *
b1010001 %
1$
#810000
0$
#815000
b10000 #
b10000 (
b1010010 %
b1000 3
0!
0.
b10000 ,
1"
1-
1$
#820000
0$
#825000
b100 3
1!
1.
b100000 *
b1010011 %
1$
#830000
0$
#835000
b11000101 #
b11000101 (
b1010100 %
b1000 3
0!
0.
b11000101 ,
0"
0-
1$
#840000
0$
#845000
b100 3
1!
1.
b100001 *
b1010101 %
1$
#850000
0$
#855000
b111110 #
b111110 (
b1010110 %
b1000 3
0!
0.
b111110 ,
1"
1-
1$
#860000
0$
#865000
b100 3
1!
1.
b100010 *
b1010111 %
1$
#870000
0$
#875000
b101000 #
b101000 (
b1011000 %
b1000 3
0!
0.
b101000 ,
1$
#880000
0$
#885000
b100 3
1!
1.
b100011 *
b1011001 %
1$
#890000
0$
#895000
b11000111 #
b11000111 (
b1011010 %
b1000 3
0!
0.
b11000111 ,
0"
0-
1$
#900000
0$
#905000
b100 3
1!
1.
b100100 *
b1011011 %
1$
#910000
0$
#915000
b10000110 #
b10000110 (
b1011100 %
b1000 3
0!
0.
b10000110 ,
1"
1-
1$
#920000
0$
#925000
b100 3
1!
1.
b100101 *
b1011101 %
1$
#930000
0$
#935000
b110110 #
b110110 (
b1011110 %
b1000 3
0!
0.
b110110 ,
0"
0-
1$
#940000
0$
#945000
b100 3
1!
1.
b100110 *
b1011111 %
1$
#950000
0$
#955000
b1001000 #
b1001000 (
b1100000 %
b1000 3
0!
0.
b1001000 ,
1"
1-
1$
#960000
0$
#965000
b100 3
1!
1.
b100111 *
b1100001 %
1$
#970000
0$
#975000
b111010 #
b111010 (
b1100010 %
b1000 3
0!
0.
b111010 ,
0"
0-
1$
#980000
0$
#985000
b100 3
1!
1.
b101000 *
b1100011 %
1$
#990000
0$
#995000
b1010101 #
b1010101 (
b1100100 %
b1000 3
0!
0.
b1010101 ,
1"
1-
1$
#1000000
0$
#1005000
b100 3
1!
1.
b101001 *
b1100101 %
1$
#1010000
0$
#1015000
b10110001 #
b10110001 (
b1100110 %
b1000 3
0!
0.
b10110001 ,
0"
0-
1$
#1020000
0$
#1025000
b100 3
1!
1.
b101010 *
b1100111 %
1$
#1030000
0$
#1035000
b0 #
b0 (
b1101000 %
b1000 3
0!
0.
b0 ,
1"
1-
1$
#1040000
0$
#1045000
b100 3
1!
1.
b101011 *
b1101001 %
1$
#1050000
0$
#1055000
b11000 #
b11000 (
b1101010 %
b1000 3
0!
0.
b11000 ,
1$
#1060000
0$
#1065000
b100 3
1!
1.
b101100 *
b1101011 %
1$
#1070000
0$
#1075000
b10110110 #
b10110110 (
b1101100 %
b1000 3
0!
0.
b10110110 ,
0"
0-
1$
#1080000
0$
#1085000
b100 3
1!
1.
b101101 *
b1101101 %
1$
#1090000
0$
#1095000
b1000 #
b1000 (
b1101110 %
b1000 3
0!
0.
b1000 ,
1"
1-
1$
#1100000
0$
#1105000
b100 3
1!
1.
b101110 *
b1101111 %
1$
#1110000
0$
#1115000
b10000010 #
b10000010 (
b1110000 %
b1000 3
0!
0.
b10000010 ,
1$
#1120000
0$
#1125000
b100 3
1!
1.
b101111 *
b1110001 %
1$
#1130000
0$
#1135000
b100111 #
b100111 (
b1110010 %
b1000 3
0!
0.
b100111 ,
1$
#1140000
0$
#1145000
b100 3
1!
1.
b110000 *
b1110011 %
1$
#1150000
0$
#1155000
b11110010 #
b11110010 (
b1110100 %
b1000 3
0!
0.
b11110010 ,
0"
0-
1$
#1160000
0$
#1165000
b100 3
1!
1.
b110001 *
b1110101 %
1$
#1170000
0$
#1175000
b0 #
b0 (
b1110110 %
b1000 3
0!
0.
b0 ,
1"
1-
1$
#1180000
0$
#1185000
b100 3
1!
1.
b110010 *
b1110111 %
1$
#1190000
0$
#1195000
b100110 #
b100110 (
b1111000 %
b1000 3
0!
0.
b100110 ,
0"
0-
1$
#1200000
0$
#1205000
b100 3
1!
1.
b110011 *
b1111001 %
1$
#1210000
0$
#1215000
b1 #
b1 (
b1111010 %
b1000 3
0!
0.
b1 ,
1"
1-
1$
#1220000
0$
#1225000
b100 3
1!
1.
b110100 *
b1111011 %
1$
#1230000
0$
#1235000
b11100000 #
b11100000 (
b1111100 %
b1000 3
0!
0.
b11100000 ,
0"
0-
1$
#1240000
0$
#1245000
b100 3
1!
1.
b110101 *
b1111101 %
1$
#1250000
0$
#1255000
b1111 #
b1111 (
b1111110 %
b1000 3
0!
0.
b1111 ,
1"
1-
1$
#1260000
0$
#1265000
b100 3
1!
1.
b110110 *
b1111111 %
1$
#1270000
0$
#1275000
b110001 #
b110001 (
b10000000 %
b1000 3
0!
0.
b110001 ,
1$
#1280000
0$
#1285000
b100 3
1!
1.
b110111 *
b10000001 %
1$
#1290000
0$
#1295000
b101011 #
b101011 (
b10000010 %
b1000 3
0!
0.
b101011 ,
1$
#1300000
0$
#1305000
b100 3
1!
1.
b111000 *
b10000011 %
1$
#1310000
0$
#1315000
b1100 #
b1100 (
b10000100 %
b1000 3
0!
0.
b1100 ,
1$
#1320000
0$
#1325000
b100 3
1!
1.
b111001 *
b10000101 %
1$
#1330000
0$
#1335000
b1110 #
b1110 (
b10000110 %
b1000 3
0!
0.
b1110 ,
1$
#1340000
0$
#1345000
b100 3
1!
1.
b111010 *
b10000111 %
1$
#1350000
0$
#1355000
b1000 #
b1000 (
b10001000 %
b1000 3
0!
0.
b1000 ,
1$
#1360000
0$
#1365000
b100 3
1!
1.
b111011 *
b10001001 %
1$
#1370000
0$
#1375000
b1001110 #
b1001110 (
b10001010 %
b1000 3
0!
0.
b1001110 ,
1$
#1380000
0$
#1385000
b100 3
1!
1.
b111100 *
b10001011 %
1$
#1390000
0$
#1395000
b11110001 #
b11110001 (
b10001100 %
b1000 3
0!
0.
b11110001 ,
1$
#1400000
0$
#1405000
b100 3
1!
1.
b111101 *
b10001101 %
1$
#1410000
0$
#1415000
b110111 #
b110111 (
b10001110 %
b1000 3
0!
0.
b110111 ,
1$
#1420000
0$
#1425000
b100 3
1!
1.
b111110 *
b10001111 %
1$
#1430000
0$
#1435000
b111 #
b111 (
b10010000 %
b1000 3
0!
0.
b111 ,
1$
#1440000
0$
#1445000
b100 3
1!
1.
b111111 *
b10010001 %
1$
#1450000
0$
#1455000
b10000 #
b10000 (
b10010010 %
b1000 3
0!
0.
b10000 ,
1$
#1460000
0$
#1465000
b100 3
1!
1.
b1000000 *
b10010011 %
1$
#1470000
0$
#1475000
b11 #
b11 (
b10010100 %
b1000 3
0!
0.
b11 ,
1$
#1480000
0$
#1485000
b100 3
1!
1.
b1000001 *
b10010101 %
1$
#1490000
0$
#1495000
b1110 #
b1110 (
b10010110 %
b1000 3
0!
0.
b1110 ,
1$
#1500000
0$
#1505000
b100 3
1!
1.
b1000010 *
b10010111 %
1$
#1510000
0$
#1515000
b1001 #
b1001 (
b10011000 %
b1000 3
0!
0.
b1001 ,
1$
#1520000
0$
#1525000
b100 3
1!
1.
b1000011 *
b10011001 %
1$
#1530000
0$
#1535000
b0 #
b0 (
b10011010 %
b1000 3
0!
0.
b0 ,
1$
#1540000
0$
#1545000
b100 3
1!
1.
b1000100 *
b10011011 %
1$
#1550000
0$
#1555000
b11100001 #
b11100001 (
b10011100 %
b1000 3
0!
0.
b11100001 ,
0"
0-
1$
#1560000
0$
#1565000
b100 3
1!
1.
b1000101 *
b10011101 %
1$
#1570000
0$
#1575000
b0 #
b0 (
b10011110 %
b1000 3
0!
0.
b0 ,
1"
1-
1$
#1580000
0$
#1585000
b100 3
1!
1.
b1000110 *
b10011111 %
1$
#1590000
0$
#1595000
b1110 #
b1110 (
b10100000 %
b1000 3
0!
0.
b1110 ,
1$
#1600000
0$
#1605000
b100 3
1!
1.
b1000111 *
b10100001 %
1$
#1610000
0$
#1615000
b10100 #
b10100 (
b10100010 %
b1000 3
0!
0.
b10100 ,
1$
#1620000
0$
#1625000
b100 3
1!
1.
b1001000 *
b10100011 %
1$
#1630000
0$
#1635000
b11 #
b11 (
b10100100 %
b1000 3
0!
0.
b11 ,
1$
#1640000
0$
#1645000
b100 3
1!
1.
b1001001 *
b10100101 %
1$
#1650000
0$
#1655000
b10001 #
b10001 (
b10100110 %
b1000 3
0!
0.
b10001 ,
1$
#1660000
0$
#1665000
b100 3
1!
1.
b1001010 *
b10100111 %
1$
#1670000
0$
#1675000
b111 #
b111 (
b10101000 %
b1000 3
0!
0.
b111 ,
1$
#1680000
0$
#1685000
b100 3
1!
1.
b1001011 *
b10101001 %
1$
#1690000
0$
#1695000
b110001 #
b110001 (
b10101010 %
b1000 3
0!
0.
b110001 ,
1$
#1700000
0$
#1705000
b100 3
1!
1.
b1001100 *
b10101011 %
1$
#1710000
0$
#1715000
b11000001 #
b11000001 (
b10101100 %
b1000 3
0!
0.
b11000001 ,
1$
#1720000
0$
#1725000
b100 3
1!
1.
b1001101 *
b10101101 %
1$
#1730000
0$
#1735000
b1001000 #
b1001000 (
b10101110 %
b1000 3
0!
0.
b1001000 ,
1$
#1740000
0$
#1745000
b100 3
1!
1.
b1001110 *
b10101111 %
1$
#1750000
0$
#1755000
b1000 #
b1000 (
b10110000 %
b1000 3
0!
0.
b1000 ,
1$
#1760000
0$
#1765000
b100 3
1!
1.
b1001111 *
b10110001 %
1$
#1770000
0$
#1775000
b1111 #
b1111 (
b10110010 %
b1000 3
0!
0.
b1111 ,
1$
#1780000
0$
#1785000
b100 3
1!
1.
b1010000 *
b10110011 %
1$
#1790000
0$
#1795000
b1100 #
b1100 (
b10110100 %
b1000 3
0!
0.
b1100 ,
1$
#1800000
0$
#1805000
b100 3
1!
1.
b1010001 *
b10110101 %
1$
#1810000
0$
#1815000
b110001 #
b110001 (
b10110110 %
b1000 3
0!
0.
b110001 ,
1$
#1820000
0$
#1825000
b100 3
1!
1.
b1010010 *
b10110111 %
1$
#1830000
0$
#1835000
b110110 #
b110110 (
b10111000 %
b1000 3
0!
0.
b110110 ,
1$
#1840000
0$
#1845000
b100 3
1!
1.
b1010011 *
b10111001 %
1$
#1850000
0$
#1855000
b1111 #
b1111 (
b10111010 %
b1000 3
0!
0.
b1111 ,
1$
#1860000
0$
#1865000
b100 3
1!
1.
b1010100 *
b10111011 %
1$
#1870000
0$
#1875000
b10001 #
b10001 (
b10111100 %
b1000 3
0!
0.
b10001 ,
0"
0-
1$
#1880000
0$
#1885000
b100 3
1!
1.
b1010101 *
b10111101 %
1$
#1890000
0$
#1895000
b101001 #
b101001 (
b10111110 %
b1000 3
0!
0.
b101001 ,
1$
#1900000
0$
#1905000
b100 3
1!
1.
b1010110 *
b10111111 %
1$
#1910000
0$
#1915000
b110110 #
b110110 (
b11000000 %
b1000 3
0!
0.
b110110 ,
1$
#1920000
0$
#1925000
b100 3
1!
1.
b1010111 *
b11000001 %
1$
#1930000
0$
#1935000
b1000 #
b1000 (
b11000010 %
b1000 3
0!
0.
b1000 ,
1"
1-
1$
#1940000
0$
#1945000
b100 3
1!
1.
b1011000 *
b11000011 %
1$
#1950000
0$
#1955000
b101010 #
b101010 (
b11000100 %
b1000 3
0!
0.
b101010 ,
0"
0-
1$
#1960000
0$
#1965000
b100 3
1!
1.
b1011001 *
b11000101 %
1$
#1970000
0$
#1975000
b0 #
b0 (
b11000110 %
b1000 3
0!
0.
b0 ,
1"
1-
1$
#1980000
0$
#1985000
b100 3
1!
1.
b1011010 *
b11000111 %
1$
#1990000
0$
#1995000
b11001000 %
b1000 3
0!
0.
1$
#2000000
0$
